MANIFEST.in
README.md
setup.py
danemco_fabric/__init__.py
danemco_fabric/__init__.pyc
danemco_fabric/base.py
danemco_fabric/base.pyc
danemco_fabric/build.py
danemco_fabric/build.pyc
danemco_fabric/ci.py
danemco_fabric/ci.pyc
danemco_fabric/config.py
danemco_fabric/config.pyc
danemco_fabric/deploy.py
danemco_fabric/deploy.pyc
danemco_fabric/fabfile.py
danemco_fabric/test.py
danemco_fabric/test.pyc
danemco_fabric/vc.py
danemco_fabric/vc.pyc
danemco_fabric/version.py
danemco_fabric/version.pyc
danemco_fabric.egg-info/PKG-INFO
danemco_fabric.egg-info/SOURCES.txt
danemco_fabric.egg-info/dependency_links.txt
danemco_fabric.egg-info/pbr.json
danemco_fabric.egg-info/requires.txt
danemco_fabric.egg-info/top_level.txt
danemco_fabric/management/__init__.py
danemco_fabric/management/commands/__init__.py
danemco_fabric/management/commands/clear_cache.py