Metadata-Version: 1.0
Name: danemco-fabric
Version: 0.12.7
Summary: A collection of fabric utils
Home-page: https://gitlab.com/virgodev/lib/danemco-fabric.git
Author: Danemco, LLC
Author-email: dev@velocitywebworks.com
License: UNKNOWN
Platform: UNKNOWN
